shadocs/404.html
shadocs/__init__.py
shadocs/base.html
shadocs/breadcrumbs.html
shadocs/footer.html
shadocs/main.html
shadocs/mkdocs_theme.yml
shadocs/nav-sub.html
shadocs/nav.html
shadocs/search.html
shadocs/searchbox.html
shadocs/toc.html
shadocs/versions.html
shadocs/css/highlight.css
shadocs/css/highlight.min.css
shadocs/css/pygments.css
shadocs/css/pygments_dark.css
shadocs/css/shadocs.css
shadocs/css/shaphinx-extensions.css
shadocs/css/shaphinx-extensions.css.map
shadocs/css/shaphinx.css
shadocs/css/shaphinx.css.map
shadocs/fonts/fontawesome-webfont.eot
shadocs/fonts/fontawesome-webfont.svg
shadocs/fonts/fontawesome-webfont.ttf
shadocs/fonts/fontawesome-webfont.woff
shadocs/img/favicon.ico
shadocs/img/logo.png
shadocs/img/logo.svg
shadocs/js/doctools.js
shadocs/js/documentation_options.js
shadocs/js/gumshoe.js
shadocs/js/jquery-2.1.1.min.js
shadocs/js/jquery.slimscroll.min.js
shadocs/js/main.js
shadocs/js/modernizr-2.8.3.min.js
shadocs/js/searchtools.js
shadocs/js/theme.js
shadocs/js/underscore.js
shadocs/partials/_head_css_variables.html
shadocs/partials/icons.html
shadocs/sidebar/brand.html
shadocs/sidebar/ethical-ads.html
shadocs/sidebar/navigation.html
shadocs/sidebar/rtd-versions.html
shadocs/sidebar/scroll-end.html
shadocs/sidebar/scroll-start.html
shadocs/sidebar/search.html
shadocs-1.0.3.dist-info/LICENSE
shadocs-1.0.3.dist-info/METADATA
shadocs-1.0.3.dist-info/WHEEL
shadocs-1.0.3.dist-info/entry_points.txt
shadocs-1.0.3.dist-info/top_level.txt
shadocs-1.0.3.dist-info/RECORD
