Metadata-Version: 2.1
Name: shadocs
Version: 1.0.3
Summary: Cookiecutter ShaPackage 包含创建Python包所需的所有模板文件。
Home-page: https://github.com/llango/shadocs
Author: Rontom ai
Author-email: rontomai@gmail.com
License: MIT license
Keywords: shadocs
Classifier: Development Status :: 2 - Pre-Alpha
Classifier: Intended Audience :: Developers
Classifier: License :: OSI Approved :: MIT License
Classifier: Natural Language :: English
Classifier: Programming Language :: Python :: 3
Classifier: Programming Language :: Python :: 3.5
Classifier: Programming Language :: Python :: 3.6
Classifier: Programming Language :: Python :: 3.7
Classifier: Programming Language :: Python :: 3.8
Requires-Python: >=3.5
License-File: LICENSE
Requires-Dist: Click (>=7.0)
